medali/__init__.py
medali/core.py
medali/lib/advisory_flagging/V01.ini
medali/lib/advisory_flagging/V1M0.ini
medali/lib/advisory_flagging/V1M1.ini
medali/lib/harmonic_params/V01.ini
medali/lib/harmonic_params/V1M0.ini
medali/lib/harmonic_params/V1M1.ini
medali/lib/s1_sigma/plia/V01.ini
medali/lib/s1_sigma/plia/V1M0.ini
medali/lib/s1_sigma/plia/V1M1.ini
medali/lib/s1_sigma/sig0/V01.ini
medali/lib/s1_sigma/sig0/V1M0.ini
medali/lib/s1_sigma/sig0/V1M1.ini
medali/lib/s1dc_flood_mapper/V01.ini
medali/lib/s1dc_flood_mapper/V1M0.ini
medali/lib/s1dc_flood_mapper/V1M1.ini
medali/lib/s1dc_flood_mapper/V1M2.ini
medali/lib/tempinator/V01.ini
medali/lib/tempinator/V1M0.ini
medali-0.2.8.dist-info/AUTHORS.rst
medali-0.2.8.dist-info/LICENSE.txt
medali-0.2.8.dist-info/METADATA
medali-0.2.8.dist-info/WHEEL
medali-0.2.8.dist-info/top_level.txt
medali-0.2.8.dist-info/RECORD
