Metadata-Version: 2.1
Name: medali
Version: 0.2.8
Summary: medali is responsible for parsing, tagging and interpreting product metadata
Home-page: https://github.com/TUW-GEO/medali
Author: TU Wien GEO MRS group
Author-email: remote.sensing@geo.tuwien.ac.at
License: mit
Keywords: Metadata
Platform: any
Classifier: Development Status :: 4 - Beta
Classifier: License :: OSI Approved :: MIT License
Classifier: Topic :: Scientific/Engineering
Classifier: Topic :: Software Development :: Version Control :: Git
Classifier: Programming Language :: Python :: 3.6
Classifier: Natural Language :: English
Provides-Extra: testing
Requires-Dist: pytest ; extra == 'testing'
Requires-Dist: pytest-cov ; extra == 'testing'
